image_evaluator/__init__.py
image_evaluator/arcface_dist_predictor.py
image_evaluator/clip_score_predictor.py
image_evaluator/laion_ai_aesthetic_predictor.py
image_evaluator/main.py
image_evaluator-0.0.2.dist-info/LICENSE
image_evaluator-0.0.2.dist-info/METADATA
image_evaluator-0.0.2.dist-info/WHEEL
image_evaluator-0.0.2.dist-info/entry_points.txt
image_evaluator-0.0.2.dist-info/RECORD
