Metadata-Version: 2.3
Name: image-evaluator
Version: 0.0.2
Summary: An automatic image evaluation script
License: MIT
Author: neverbiasu
Requires-Python: >=3.8,<4.0
Classifier: License :: OSI Approved :: MIT License
Classifier: Programming Language :: Python :: 3
Classifier: Programming Language :: Python :: 3.8
Classifier: Programming Language :: Python :: 3.9
Classifier: Programming Language :: Python :: 3.10
Classifier: Programming Language :: Python :: 3.11
Classifier: Programming Language :: Python :: 3.12
Classifier: Programming Language :: Python :: 3.13
Requires-Dist: clip-score
Requires-Dist: insightface
Requires-Dist: numpy
Requires-Dist: onnxruntime-gpu
Requires-Dist: open-clip-torch
Requires-Dist: pillow
Requires-Dist: torch (>=1.7.0)
Requires-Dist: tqdm
Requires-Dist: transformers
